statworx_theme/__init__.py
statworx_theme/colormaps.py
statworx_theme/colors.py
statworx_theme/py.typed
statworx_theme/styles/statworx.mplstyle
statworx_theme/utils.py
statworx_theme-2.0.2.dist-info/LICENSE
statworx_theme-2.0.2.dist-info/METADATA
statworx_theme-2.0.2.dist-info/WHEEL
statworx_theme-2.0.2.dist-info/RECORD
