Metadata-Version: 2.1
Name: statworx_theme
Version: 2.0.2
Summary: A color theme for matplotlib using the offical statworx design
Home-page: https://statworx-theme.readthedocs.io/en/latest
License: MIT
Keywords: theme,matplotlib,plotting,statworx
Author: statworx Team
Author-email: accounts@statworx.com
Requires-Python: >=3.9,<4.0
Classifier: License :: OSI Approved :: MIT License
Classifier: Programming Language :: Python :: 3
Classifier: Programming Language :: Python :: 3.9
Classifier: Programming Language :: Python :: 3.10
Classifier: Programming Language :: Python :: 3.11
Classifier: Programming Language :: Python :: 3.12
Provides-Extra: altair
Provides-Extra: plotly
Requires-Dist: altair (>=5.2.0) ; extra == "altair"
Requires-Dist: nbformat (>=5.4.0) ; extra == "plotly"
Requires-Dist: plotly (>=5.10.0) ; extra == "plotly"
Requires-Dist: seaborn (>=0.11.2)
Requires-Dist: statsmodels (>=0.13.0) ; extra == "plotly"
Requires-Dist: vega-datasets (>=0.9.0) ; extra == "altair"
Project-URL: Repository, https://github.com/STATWORX/statworx-theme
